{
  "name": "Snel Offerte v2",
  "short_name": "Snel Offerte v2",
  "background_color": "#008eff",
  "orientation": "portrait",
  "display": "standalone",
  "scope": "./",
  "start_url": "./",
  "icons": [
    {
      "src": "appimages/ios/192.png",
      "sizes": "192x192",
      "type": "image/png",
      "purpose": "maskable any"
    },
    {
      "src": "appimages/ios/app-logo-180.png",
      "sizes": "180x180",
      "type": "image/png",
      "purpose": "maskable any"
    },
    {
      "src": "appimages/ios/app-logo-512.png",
      "sizes": "512x512",
      "type": "image/png",
      "purpose": "maskable"
    },
    {
      "src": "appimages/ios/app-logo-512.png",
      "sizes": "512x512",
      "type": "image/png"
    }
  ]
}
